{"stats":{"minecraft:used":{"minecraft:netherite_boots":1,"minecraft:cow_spawn_egg":45,"minecraft:firework_rocket":14,"minecraft:netherite_leggings":1,"minecraft:netherite_chestplate":5,"minecraft:elytra":2,"minecraft:pig_spawn_egg":43,"minecraft:netherite_helmet":4,"minecraft:cooked_beef":3},"minecraft:crafted":{"minecraft:air":0},"minecraft:custom":{"minecraft:time_since_rest":19372,"minecraft:open_chest":6,"minecraft:interact_with_smithing_table":4,"minecraft:crouch_one_cm":941,"minecraft:sprint_one_cm":41036,"minecraft:play_time":19372,"minecraft:open_shulker_box":12,"minecraft:damage_taken":265,"minecraft:walk_one_cm":15249,"minecraft:sneak_time":102,"minecraft:interact_with_anvil":1,"minecraft:aviate_one_cm":448096,"minecraft:jump":161,"minecraft:interact_with_blast_furnace":1,"minecraft:leave_game":2,"minecraft:walk_on_water_one_cm":365,"minecraft:time_since_death":19372,"minecraft:total_world_time":19372,"minecraft:damage_resisted":20,"minecraft:fall_one_cm":3414,"minecraft:fly_one_cm":65742}},"DataVersion":3465}